django_payment_payir-0.3.dist-info/DESCRIPTION.rst
django_payment_payir-0.3.dist-info/METADATA
django_payment_payir-0.3.dist-info/RECORD
django_payment_payir-0.3.dist-info/WHEEL
django_payment_payir-0.3.dist-info/metadata.json
django_payment_payir-0.3.dist-info/top_level.txt
pay_ir/__init__.py
pay_ir/admin.py
pay_ir/apps.py
pay_ir/models.py
pay_ir/tests.py
pay_ir/urls.py
pay_ir/views.py
pay_ir/migrations/0001_initial.py
pay_ir/migrations/__init__.py
pay_ir/static/css/payment-pay-ir.css
pay_ir/static/icon/heart.svg
pay_ir/templates/base.html
pay_ir/templates/duplicate.html
pay_ir/templates/fail.html
pay_ir/templates/index.html
pay_ir/templates/success.html
